{"name":"考试","slug":"考试","count":4,"postlist":[{"title":"linux题库","uid":"e8eb3a6ab0f5bbc8166f7c80111edbc0","slug":"linux题库","date":"2022-12-06T10:06:34.000Z","updated":"2022-12-07T13:16:53.158Z","comments":true,"path":"api/articles/linux题库.json","keywords":null,"cover":"https://images.alphacoders.com/998/998077.jpg","text":"Linux操作系统课后习题答案1.10 练习题一、填空题1．GNU的含义是GNU’s Not Unix的递归缩写。 2．Linux一般有3个主要部分： 内核 、 命令解释层 、 实用工具 。 3．**&#x2F;etc&#x2F;sysconfig&#x2F;network** ...","link":"","photos":[],"count_time":{"symbolsCount":"11k","symbolsTime":"10 mins."},"categories":[{"name":"考试","slug":"考试","count":4,"path":"api/categories/考试.json"}],"tags":[{"name":"考试","slug":"考试","count":4,"path":"api/tags/考试.json"}],"author":{"name":"Leixng","slug":"blog-author","avatar":"/img/003.png","link":"/","description":"清风徐来","socials":{"github":"https://github.com/leixingssr?tab=repositories","twitter":"","stackoverflow":"","wechat":"","qq":"","weibo":"","zhihu":"","csdn":"","juejin":"","customs":{"bilibili":{"icon":"/img/svg/bilibili.svg","link":"https://space.bilibili.com/177137946?spm_id_from=333.1007.0.0"},"gitee":{"icon":"/img/svg/gitee.svg","link":"https://gitee.com/leixingsss"},"Email":{"icon":"/img/svg/QQMail.svg","link":"https://mail.qq.com/cgi-bin/frame_html?sid=E8RhG3WmM8OPiglq&r=af46ab161c61f3640e812141ff04c53c&lang=zh"}}}}},{"title":"软件设计2016A","uid":"0f532b7b772da326c49235c97b678ef4","slug":"软件设计2016A","date":"2022-12-06T06:50:31.000Z","updated":"2022-12-07T13:15:09.701Z","comments":true,"path":"api/articles/软件设计2016A.json","keywords":null,"cover":"https://images2.alphacoders.com/696/696695.png","text":"软件设计A选择题设计模式一般是用来解决什么问题的（ D ）。A．需求获取中业务领域知识获取 B．测试用例的设计C．编码中如何组织代码 D．同一问题的不同表象 开闭原则的含义是一个软件实体（ A ）。A．应该对扩展开发，对修改关闭 B．对修改开放，对扩展关闭C．在应用子类的地方可以...","link":"","photos":[],"count_time":{"symbolsCount":"2.8k","symbolsTime":"3 mins."},"categories":[{"name":"考试","slug":"考试","count":4,"path":"api/categories/考试.json"}],"tags":[{"name":"考试","slug":"考试","count":4,"path":"api/tags/考试.json"}],"author":{"name":"Leixng","slug":"blog-author","avatar":"/img/003.png","link":"/","description":"清风徐来","socials":{"github":"https://github.com/leixingssr?tab=repositories","twitter":"","stackoverflow":"","wechat":"","qq":"","weibo":"","zhihu":"","csdn":"","juejin":"","customs":{"bilibili":{"icon":"/img/svg/bilibili.svg","link":"https://space.bilibili.com/177137946?spm_id_from=333.1007.0.0"},"gitee":{"icon":"/img/svg/gitee.svg","link":"https://gitee.com/leixingsss"},"Email":{"icon":"/img/svg/QQMail.svg","link":"https://mail.qq.com/cgi-bin/frame_html?sid=E8RhG3WmM8OPiglq&r=af46ab161c61f3640e812141ff04c53c&lang=zh"}}}}},{"title":"习近平中国特色社会主义思想","uid":"96a221f996d4d1c6cc256ac4ea5a1298","slug":"习近平中国特色社会主义思想","date":"2022-12-07T12:53:34.000Z","updated":"2022-12-07T13:14:31.338Z","comments":true,"path":"api/articles/习近平中国特色社会主义思想.json","keywords":null,"cover":"https://images6.alphacoders.com/992/992249.jpg","text":"习近平中国特色社会主义思想全面推进依法治国,涉及立法、执法、司法、守法等各个方面,涉及中国特色社会主义事业“五位一体”总体布局的各个领域,必须加强顶层设计、统筹谋划,在实际工作中必须有一个总揽全局、牵引各方的总抓手。全面依法治国的总抓手是()• A、依法治国和以德治国相结合• B...","link":"","photos":[],"count_time":{"symbolsCount":"4.1k","symbolsTime":"4 mins."},"categories":[{"name":"考试","slug":"考试","count":4,"path":"api/categories/考试.json"}],"tags":[{"name":"考试","slug":"考试","count":4,"path":"api/tags/考试.json"}],"author":{"name":"Leixng","slug":"blog-author","avatar":"/img/003.png","link":"/","description":"清风徐来","socials":{"github":"https://github.com/leixingssr?tab=repositories","twitter":"","stackoverflow":"","wechat":"","qq":"","weibo":"","zhihu":"","csdn":"","juejin":"","customs":{"bilibili":{"icon":"/img/svg/bilibili.svg","link":"https://space.bilibili.com/177137946?spm_id_from=333.1007.0.0"},"gitee":{"icon":"/img/svg/gitee.svg","link":"https://gitee.com/leixingsss"},"Email":{"icon":"/img/svg/QQMail.svg","link":"https://mail.qq.com/cgi-bin/frame_html?sid=E8RhG3WmM8OPiglq&r=af46ab161c61f3640e812141ff04c53c&lang=zh"}}}}},{"title":"软件设计2016B","uid":"1e4363102957705e71b03727a248bf78","slug":"软件设计2016B","date":"2022-12-06T07:01:51.000Z","updated":"2022-12-07T13:15:49.338Z","comments":true,"path":"api/articles/软件设计2016B.json","keywords":null,"cover":"https://images7.alphacoders.com/112/1123196.png","text":"软件设计B选择题（每小题2分，共30分）对于依赖倒转的表述错误的是（ D ）A. 依赖于抽象而不依赖于具体，也就是针对接口编程。B. 依赖倒转的接口并非语法意义上的接口，而是，一个类对其他对象进行调用时，所知道的方法集合。C. 从选项B的角度论述，一个对象可以有多个接口。D. 此...","link":"","photos":[],"count_time":{"symbolsCount":"3.2k","symbolsTime":"3 mins."},"categories":[{"name":"考试","slug":"考试","count":4,"path":"api/categories/考试.json"}],"tags":[{"name":"考试","slug":"考试","count":4,"path":"api/tags/考试.json"}],"author":{"name":"Leixng","slug":"blog-author","avatar":"/img/003.png","link":"/","description":"清风徐来","socials":{"github":"https://github.com/leixingssr?tab=repositories","twitter":"","stackoverflow":"","wechat":"","qq":"","weibo":"","zhihu":"","csdn":"","juejin":"","customs":{"bilibili":{"icon":"/img/svg/bilibili.svg","link":"https://space.bilibili.com/177137946?spm_id_from=333.1007.0.0"},"gitee":{"icon":"/img/svg/gitee.svg","link":"https://gitee.com/leixingsss"},"Email":{"icon":"/img/svg/QQMail.svg","link":"https://mail.qq.com/cgi-bin/frame_html?sid=E8RhG3WmM8OPiglq&r=af46ab161c61f3640e812141ff04c53c&lang=zh"}}}}}]}