{"name":"面试","slug":"面试","count":5,"postlist":[{"title":"面试","uid":"b8cee04dc0368bcbafd67939edc1c0b9","slug":"面试","date":"2023-03-13T14:03:10.000Z","updated":"2023-07-24T12:50:36.200Z","comments":true,"path":"api/articles/面试.json","keywords":null,"cover":"https://images5.alphacoders.com/131/1318231.png","text":"分享我的经验和曾经遇到的问题.........","link":"","photos":[],"count_time":{"symbolsCount":"9.5k","symbolsTime":"9 mins."},"categories":[{"name":"面试","slug":"面试","count":5,"path":"api/categories/面试.json"}],"tags":[{"name":"面试","slug":"面试","count":5,"path":"api/tags/面试.json"}],"author":{"name":"Leixng","slug":"blog-author","avatar":"/img/003.png","link":"/","description":"清风徐来","socials":{"github":"https://github.com/leixingssr?tab=repositories","twitter":"","stackoverflow":"","wechat":"","qq":"","weibo":"","zhihu":"","csdn":"","juejin":"","customs":{"bilibili":{"icon":"/img/svg/bilibili.svg","link":"https://space.bilibili.com/177137946?spm_id_from=333.1007.0.0"},"gitee":{"icon":"/img/svg/gitee.svg","link":"https://gitee.com/leixingsss"},"Email":{"icon":"/img/svg/QQMail.svg","link":"https://mail.qq.com/cgi-bin/frame_html?sid=E8RhG3WmM8OPiglq&r=af46ab161c61f3640e812141ff04c53c&lang=zh"}}}},"feature":"ture"},{"title":"Redis面试","uid":"9864cb5f05af74d955a88eab7d87ec93","slug":"Redis面试","date":"2023-02-24T14:06:48.000Z","updated":"2023-02-24T14:53:49.234Z","comments":true,"path":"api/articles/Redis面试.json","keywords":null,"cover":"https://images2.alphacoders.com/648/648566.jpg#文章在首页时的预览图，以及文章页的背景图","text":"分享我的经验和曾经遇到的问题.........","link":"","photos":[],"count_time":{"symbolsCount":"1.1k","symbolsTime":"1 mins."},"categories":[{"name":"面试","slug":"面试","count":5,"path":"api/categories/面试.json"}],"tags":[{"name":"面试","slug":"面试","count":5,"path":"api/tags/面试.json"}],"author":{"name":"Leixng","slug":"blog-author","avatar":"/img/003.png","link":"/","description":"清风徐来","socials":{"github":"https://github.com/leixingssr?tab=repositories","twitter":"","stackoverflow":"","wechat":"","qq":"","weibo":"","zhihu":"","csdn":"","juejin":"","customs":{"bilibili":{"icon":"/img/svg/bilibili.svg","link":"https://space.bilibili.com/177137946?spm_id_from=333.1007.0.0"},"gitee":{"icon":"/img/svg/gitee.svg","link":"https://gitee.com/leixingsss"},"Email":{"icon":"/img/svg/QQMail.svg","link":"https://mail.qq.com/cgi-bin/frame_html?sid=E8RhG3WmM8OPiglq&r=af46ab161c61f3640e812141ff04c53c&lang=zh"}}}},"feature":"ture"},{"title":"Mysql面试","uid":"5c9c7d24e42be581f1bc83d2d55ba0fd","slug":"Mysql面试","date":"2023-02-24T14:06:20.000Z","updated":"2023-03-02T09:42:05.616Z","comments":true,"path":"api/articles/Mysql面试.json","keywords":null,"cover":"https://images.alphacoders.com/640/640985.jpg#文章在首页时的预览图，以及文章页的背景图","text":"分享我的经验和曾经遇到的问题.........","link":"","photos":[],"count_time":{"symbolsCount":"1.9k","symbolsTime":"2 mins."},"categories":[{"name":"面试","slug":"面试","count":5,"path":"api/categories/面试.json"}],"tags":[{"name":"面试","slug":"面试","count":5,"path":"api/tags/面试.json"}],"author":{"name":"Leixng","slug":"blog-author","avatar":"/img/003.png","link":"/","description":"清风徐来","socials":{"github":"https://github.com/leixingssr?tab=repositories","twitter":"","stackoverflow":"","wechat":"","qq":"","weibo":"","zhihu":"","csdn":"","juejin":"","customs":{"bilibili":{"icon":"/img/svg/bilibili.svg","link":"https://space.bilibili.com/177137946?spm_id_from=333.1007.0.0"},"gitee":{"icon":"/img/svg/gitee.svg","link":"https://gitee.com/leixingsss"},"Email":{"icon":"/img/svg/QQMail.svg","link":"https://mail.qq.com/cgi-bin/frame_html?sid=E8RhG3WmM8OPiglq&r=af46ab161c61f3640e812141ff04c53c&lang=zh"}}}},"feature":"ture"},{"title":"框架面试","uid":"ad513d9238aebc54d31cd7ff3f640644","slug":"框架面试","date":"2023-02-24T14:06:01.000Z","updated":"2023-03-14T14:05:03.649Z","comments":true,"path":"api/articles/框架面试.json","keywords":null,"cover":"https://img.99tu.com:9988/uploads/allimg/201124/2-201124213320.jpg#文章在首页时的预览图，以及文章页的背景图","text":"分享我的经验和曾经遇到的问题.........","link":"","photos":[],"count_time":{"symbolsCount":"2.3k","symbolsTime":"2 mins."},"categories":[{"name":"面试","slug":"面试","count":5,"path":"api/categories/面试.json"}],"tags":[{"name":"面试","slug":"面试","count":5,"path":"api/tags/面试.json"}],"author":{"name":"Leixng","slug":"blog-author","avatar":"/img/003.png","link":"/","description":"清风徐来","socials":{"github":"https://github.com/leixingssr?tab=repositories","twitter":"","stackoverflow":"","wechat":"","qq":"","weibo":"","zhihu":"","csdn":"","juejin":"","customs":{"bilibili":{"icon":"/img/svg/bilibili.svg","link":"https://space.bilibili.com/177137946?spm_id_from=333.1007.0.0"},"gitee":{"icon":"/img/svg/gitee.svg","link":"https://gitee.com/leixingsss"},"Email":{"icon":"/img/svg/QQMail.svg","link":"https://mail.qq.com/cgi-bin/frame_html?sid=E8RhG3WmM8OPiglq&r=af46ab161c61f3640e812141ff04c53c&lang=zh"}}}},"feature":"ture"},{"title":"Java面试","uid":"23ac8df41cab07b7baa7284b723ffed2","slug":"Java面试","date":"2023-02-24T14:05:35.000Z","updated":"2023-07-26T14:15:18.097Z","comments":true,"path":"api/articles/Java面试.json","keywords":null,"cover":"https://images.alphacoders.com/603/603479.png","text":"最好的面试...","link":"","photos":[],"count_time":{"symbolsCount":"4.8k","symbolsTime":"4 mins."},"categories":[{"name":"面试","slug":"面试","count":5,"path":"api/categories/面试.json"}],"tags":[{"name":"面试","slug":"面试","count":5,"path":"api/tags/面试.json"}],"author":{"name":"Leixng","slug":"blog-author","avatar":"/img/003.png","link":"/","description":"清风徐来","socials":{"github":"https://github.com/leixingssr?tab=repositories","twitter":"","stackoverflow":"","wechat":"","qq":"","weibo":"","zhihu":"","csdn":"","juejin":"","customs":{"bilibili":{"icon":"/img/svg/bilibili.svg","link":"https://space.bilibili.com/177137946?spm_id_from=333.1007.0.0"},"gitee":{"icon":"/img/svg/gitee.svg","link":"https://gitee.com/leixingsss"},"Email":{"icon":"/img/svg/QQMail.svg","link":"https://mail.qq.com/cgi-bin/frame_html?sid=E8RhG3WmM8OPiglq&r=af46ab161c61f3640e812141ff04c53c&lang=zh"}}}},"feature":"ture"}]}